<?xml version="1.0" encoding="UTF-8"?><record_update>
    <sys_choice action="INSERT_OR_UPDATE" field="promoted_uat_state" table="x_417679_devtrack_development" version="3">
        <sys_choice action="INSERT_OR_UPDATE">
            <dependent_value/>
            <element>promoted_uat_state</element>
            <hint/>
            <inactive>false</inactive>
            <label>Not Promoted</label>
            <language>en</language>
            <name>x_417679_devtrack_development</name>
            <sequence>0</sequence>
            <sys_created_by>admin</sys_created_by>
            <sys_created_on>2020-05-13 21:57:20</sys_created_on>
            <sys_domain>global</sys_domain>
            <sys_domain_path>/</sys_domain_path>
            <sys_id>28ba894d07b45010d318fd1e7c1ed03d</sys_id>
            <sys_mod_count>2</sys_mod_count>
            <sys_updated_by>admin</sys_updated_by>
            <sys_updated_on>2020-05-13 21:58:34</sys_updated_on>
            <value>0</value>
        </sys_choice>
        <sys_choice action="INSERT_OR_UPDATE">
            <dependent_value/>
            <element>promoted_uat_state</element>
            <hint/>
            <inactive>false</inactive>
            <label>Scheduled</label>
            <language>en</language>
            <name>x_417679_devtrack_development</name>
            <sequence>5</sequence>
            <sys_created_by>admin</sys_created_by>
            <sys_created_on>2020-05-13 21:57:32</sys_created_on>
            <sys_domain>global</sys_domain>
            <sys_domain_path>/</sys_domain_path>
            <sys_id>adcac94d07b45010d318fd1e7c1ed013</sys_id>
            <sys_mod_count>2</sys_mod_count>
            <sys_updated_by>admin</sys_updated_by>
            <sys_updated_on>2020-05-13 21:58:36</sys_updated_on>
            <value>5</value>
        </sys_choice>
        <sys_choice action="INSERT_OR_UPDATE">
            <dependent_value/>
            <element>promoted_uat_state</element>
            <hint/>
            <inactive>false</inactive>
            <label>Pending Change</label>
            <language>en</language>
            <name>x_417679_devtrack_development</name>
            <sequence>7</sequence>
            <sys_created_by>admin</sys_created_by>
            <sys_created_on>2020-05-13 21:58:12</sys_created_on>
            <sys_domain>global</sys_domain>
            <sys_domain_path>/</sys_domain_path>
            <sys_id>79ea8d4d07b45010d318fd1e7c1ed0db</sys_id>
            <sys_mod_count>2</sys_mod_count>
            <sys_updated_by>admin</sys_updated_by>
            <sys_updated_on>2020-05-13 21:58:41</sys_updated_on>
            <value>7</value>
        </sys_choice>
        <sys_choice action="INSERT_OR_UPDATE">
            <dependent_value/>
            <element>promoted_uat_state</element>
            <hint/>
            <inactive>false</inactive>
            <label>Work In Progress</label>
            <language>en</language>
            <name>x_417679_devtrack_development</name>
            <sequence>10</sequence>
            <sys_created_by>admin</sys_created_by>
            <sys_created_on>2020-05-13 21:57:42</sys_created_on>
            <sys_domain>global</sys_domain>
            <sys_domain_path>/</sys_domain_path>
            <sys_id>0ddac94d07b45010d318fd1e7c1ed020</sys_id>
            <sys_mod_count>2</sys_mod_count>
            <sys_updated_by>admin</sys_updated_by>
            <sys_updated_on>2020-05-13 21:58:38</sys_updated_on>
            <value>10</value>
        </sys_choice>
        <sys_choice action="INSERT_OR_UPDATE">
            <dependent_value/>
            <element>promoted_uat_state</element>
            <hint/>
            <inactive>false</inactive>
            <label>Promoted</label>
            <language>en</language>
            <name>x_417679_devtrack_development</name>
            <sequence>15</sequence>
            <sys_created_by>admin</sys_created_by>
            <sys_created_on>2020-05-13 21:57:52</sys_created_on>
            <sys_domain>global</sys_domain>
            <sys_domain_path>/</sys_domain_path>
            <sys_id>53da4d4d07b45010d318fd1e7c1ed088</sys_id>
            <sys_mod_count>2</sys_mod_count>
            <sys_updated_by>admin</sys_updated_by>
            <sys_updated_on>2020-05-13 21:58:40</sys_updated_on>
            <value>15</value>
        </sys_choice>
        <sys_choice_set action="INSERT_OR_UPDATE">
            <element>promoted_uat_state</element>
            <name>x_417679_devtrack_development</name>
            <sys_class_name>sys_choice_set</sys_class_name>
            <sys_created_by>Aidan.Lovegrove</sys_created_by>
            <sys_created_on>2020-05-13 21:57:20</sys_created_on>
            <sys_id>f9ca894d07b45010d318fd1e7c1ed0a3</sys_id>
            <sys_mod_count>0</sys_mod_count>
            <sys_name>promoted_uat_state</sys_name>
            <sys_package display_value="Development Tracker" source="x_417679_devtrack">24eff4c907745010d318fd1e7c1ed0fe</sys_package>
            <sys_policy/>
            <sys_scope display_value="Development Tracker">24eff4c907745010d318fd1e7c1ed0fe</sys_scope>
            <sys_update_name>sys_choice_x_417679_devtrack_development_promoted_uat_state</sys_update_name>
            <sys_updated_by>Aidan.Lovegrove</sys_updated_by>
            <sys_updated_on>2020-05-13 21:57:20</sys_updated_on>
        </sys_choice_set>
    </sys_choice>
</record_update>
